ama_data_exporters/__init__.py
ama_data_exporters/example.py
ama_data_exporters-0.1.6.dist-info/METADATA
ama_data_exporters-0.1.6.dist-info/WHEEL
ama_data_exporters-0.1.6.dist-info/RECORD
