Metadata-Version: 2.3
Name: ama-data-exporters
Version: 0.1.6
Summary: A data-exporters framework developed by e.solutions for product AMA
Author: Muhammad Abdullah
Author-email: muhammad.abdullah@esolutions.de
Requires-Python: >=3.11,<4.0
Classifier: Programming Language :: Python :: 3
Classifier: Programming Language :: Python :: 3.11
Classifier: Programming Language :: Python :: 3.12
Classifier: Programming Language :: Python :: 3.13
Requires-Dist: atlassian-python-api (>=3.41.15,<4.0.0)
Requires-Dist: datasets (>=3.1.0,<4.0.0)
Requires-Dist: furo (>=2024.8.6,<2025.0.0)
Requires-Dist: httpx[http2] (>=0.27.0,<0.28.0)
Requires-Dist: langchain (>=0.2.15,<0.3.0)
Requires-Dist: langchain-community (>=0.2.15,<0.3.0)
Requires-Dist: langchain-text-splitters (>=0.2.2,<0.3.0)
Requires-Dist: lxml (>=5.3.0,<6.0.0)
Requires-Dist: markdown (>=3.7,<4.0)
Requires-Dist: markdownify (>=0.14.1,<0.15.0)
Requires-Dist: markitdown (>=0.0.2,<0.0.3)
Requires-Dist: nltk (>=3.9.1,<4.0.0)
Requires-Dist: openai (>=1.42.0,<2.0.0)
Requires-Dist: pillow (>=10.4.0,<11.0.0)
Requires-Dist: pymilvus (>=2.4.5,<3.0.0)
Requires-Dist: pytesseract (>=0.3.13,<0.4.0)
Requires-Dist: pyyaml (>=6.0.2,<7.0.0)
Requires-Dist: requests (>=2.32.3,<3.0.0)
Requires-Dist: sentence-transformers (>=3.4.1,<4.0.0)
Requires-Dist: sphinx (>=8.0.2,<9.0.0)
Requires-Dist: torch (>=2.6.0,<3.0.0)
